stw/__init__.py
stw/decorators.py
stw/stopwatch.py
stw/utils.py
stw-0.3.0.dist-info/METADATA
stw-0.3.0.dist-info/WHEEL
stw-0.3.0.dist-info/licenses/LICENSE
stw-0.3.0.dist-info/RECORD
