Metadata-Version: 2.4
Name: stw
Version: 0.3.0
Summary: Stopwatch library
Project-URL: Homepage, https://github.com/GulkoA/stw
Project-URL: Documentation, https://stw.readthedocs.io/en/latest
Project-URL: Issues, https://github.com/GulkoA/stw/issues
Author-email: Alex Gulko <alex@gulko.net>
License-Expression: MIT
License-File: LICENSE
Classifier: Operating System :: OS Independent
Classifier: Programming Language :: Python :: 3
Requires-Python: >=3.8
